<?xml version="1.0" encoding="utf-8"?>
<TextureAtlas imagePath="NOTE_assets-BF.png">
	<!-- Created with Adobe Animate version 20.5.1.31044 -->
	<!-- http://www.adobe.com/products/animate.html -->
	<SubTexture name="arrowDOWN 10000" x="0" y="0" width="186" height="158"/>
	<SubTexture name="arrowLEFT 10000" x="186" y="0" width="158" height="186"/>
	<SubTexture name="arrowRIGHT 10000" x="344" y="0" width="158" height="186"/>
	<SubTexture name="arrowUP 10000" x="502" y="0" width="186" height="158"/>
	<SubTexture name="down confirm 10000" x="688" y="0" width="265" height="234" frameX="0" frameY="0" frameWidth="265" frameHeight="238"/>
	<SubTexture name="down confirm 10001" x="953" y="0" width="265" height="234" frameX="0" frameY="0" frameWidth="265" frameHeight="238"/>
	<SubTexture name="down confirm 10002" x="1218" y="0" width="262" height="233" frameX="-3" frameY="-5" frameWidth="265" frameHeight="238"/>
	<SubTexture name="down confirm 10003" x="1218" y="0" width="262" height="233" frameX="-3" frameY="-5" frameWidth="265" frameHeight="238"/>
	<SubTexture name="downnote 10000" x="1480" y="0" width="187" height="159"/>
	<SubTexture name="left confirm 10000" x="1667" y="0" width="233" height="265"/>
	<SubTexture name="left confirm 10001" x="0" y="265" width="224" height="255" frameX="-4" frameY="-5" frameWidth="233" frameHeight="265"/>
	<SubTexture name="left confirm 10002" x="224" y="265" width="231" height="260" frameX="-1" frameY="-2" frameWidth="233" frameHeight="265"/>
	<SubTexture name="left confirm 10003" x="224" y="265" width="231" height="260" frameX="-1" frameY="-2" frameWidth="233" frameHeight="265"/>
	<SubTexture name="leftnote 10000" x="455" y="265" width="158" height="186"/>
	<SubTexture name="note end hold 10000" x="613" y="265" width="104" height="105"/>
	<SubTexture name="note hold piece 10000" x="717" y="265" width="50" height="44"/>
	<SubTexture name="right confirm 10000" x="767" y="265" width="229" height="261" frameX="-1" frameY="0" frameWidth="232" frameHeight="261"/>
	<SubTexture name="right confirm 10001" x="996" y="265" width="229" height="261" frameX="-1" frameY="0" frameWidth="232" frameHeight="261"/>
	<SubTexture name="right confirm 10002" x="1225" y="265" width="232" height="260" frameX="0" frameY="0" frameWidth="232" frameHeight="261"/>
	<SubTexture name="right confirm 10003" x="1225" y="265" width="232" height="260" frameX="0" frameY="0" frameWidth="232" frameHeight="261"/>
	<SubTexture name="rightnote 10000" x="1457" y="265" width="158" height="187"/>
	<SubTexture name="up confirm 10000" x="1615" y="265" width="270" height="240"/>
	<SubTexture name="up confirm 10001" x="0" y="526" width="270" height="240"/>
	<SubTexture name="up confirm 10002" x="270" y="526" width="246" height="217" frameX="-12" frameY="-12" frameWidth="270" frameHeight="240"/>
	<SubTexture name="up confirm 10003" x="270" y="526" width="246" height="217" frameX="-12" frameY="-12" frameWidth="270" frameHeight="240"/>
	<SubTexture name="upnote 10000" x="516" y="526" width="186" height="158"/>
</TextureAtlas>
